{
  "title": "Recent posts",
  "items": [
    {
      "title": "Solidity - Bit Packing",
      "permalink": "/blog/bit-packing"
    },
    {
      "title": "Solidity - Passing functions as parameters",
      "permalink": "/blog/functions-as-params"
    },
    {
      "title": "Welcome",
      "permalink": "/blog/welcome"
    },
    {
      "title": "MDX Blog Post",
      "permalink": "/blog/mdx-blog-post"
    },
    {
      "title": "Long Blog Post",
      "permalink": "/blog/long-blog-post"
    }
  ]
}