{
  "/blog-c6c": {
    "__comp": "a6aa9e1f",
    "__context": {
      "plugin": "7e520db1"
    },
    "sidebar": "814f3328",
    "items": [
      {
        "content": "115db2b3"
      },
      {
        "content": "9c814a9e"
      },
      {
        "content": "7661071f"
      },
      {
        "content": "f4f34a3a"
      },
      {
        "content": "8717b14a"
      },
      {
        "content": "925b3f96"
      }
    ],
    "metadata": "b2b675dd"
  },
  "/blog/archive-b03": {
    "__comp": "9e4087bc",
    "__context": {
      "plugin": "7e520db1"
    },
    "archive": "b2f554cd"
  },
  "/blog/bit-packing-318": {
    "__comp": "ccc49370",
    "__context": {
      "plugin": "7e520db1"
    },
    "sidebar": "814f3328",
    "content": "931a6468"
  },
  "/blog/first-blog-post-bf9": {
    "__comp": "ccc49370",
    "__context": {
      "plugin": "7e520db1"
    },
    "sidebar": "814f3328",
    "content": "e273c56f"
  },
  "/blog/functions-as-params-6af": {
    "__comp": "ccc49370",
    "__context": {
      "plugin": "7e520db1"
    },
    "sidebar": "814f3328",
    "content": "48dfe129"
  },
  "/blog/long-blog-post-248": {
    "__comp": "ccc49370",
    "__context": {
      "plugin": "7e520db1"
    },
    "sidebar": "814f3328",
    "content": "73664a40"
  },
  "/blog/mdx-blog-post-747": {
    "__comp": "ccc49370",
    "__context": {
      "plugin": "7e520db1"
    },
    "sidebar": "814f3328",
    "content": "59362658"
  },
  "/blog/tags-ced": {
    "__comp": "01a85c17",
    "__context": {
      "plugin": "7e520db1"
    },
    "sidebar": "814f3328",
    "tags": "a7023ddc"
  },
  "/blog/tags/bit-magic-775": {
    "__comp": "6875c492",
    "__context": {
      "plugin": "7e520db1"
    },
    "sidebar": "814f3328",
    "items": [
      {
        "content": "115db2b3"
      }
    ],
    "tag": "8d55d6c7",
    "listMetadata": "63cb8f10"
  },
  "/blog/tags/bit-packing-4fb": {
    "__comp": "6875c492",
    "__context": {
      "plugin": "7e520db1"
    },
    "sidebar": "814f3328",
    "items": [
      {
        "content": "115db2b3"
      }
    ],
    "tag": "73e6192b",
    "listMetadata": "6ec05a11"
  },
  "/blog/tags/docusaurus-8fd": {
    "__comp": "6875c492",
    "__context": {
      "plugin": "7e520db1"
    },
    "sidebar": "814f3328",
    "items": [
      {
        "content": "7661071f"
      },
      {
        "content": "f4f34a3a"
      },
      {
        "content": "8717b14a"
      },
      {
        "content": "925b3f96"
      }
    ],
    "tag": "a80da1cf",
    "listMetadata": "608ae6a4"
  },
  "/blog/tags/facebook-5f3": {
    "__comp": "6875c492",
    "__context": {
      "plugin": "7e520db1"
    },
    "sidebar": "814f3328",
    "items": [
      {
        "content": "7661071f"
      }
    ],
    "tag": "031793e1",
    "listMetadata": "096bfee4"
  },
  "/blog/tags/hello-a06": {
    "__comp": "6875c492",
    "__context": {
      "plugin": "7e520db1"
    },
    "sidebar": "814f3328",
    "items": [
      {
        "content": "7661071f"
      },
      {
        "content": "8717b14a"
      }
    ],
    "tag": "30a24c52",
    "listMetadata": "66406991"
  },
  "/blog/tags/hola-250": {
    "__comp": "6875c492",
    "__context": {
      "plugin": "7e520db1"
    },
    "sidebar": "814f3328",
    "items": [
      {
        "content": "925b3f96"
      }
    ],
    "tag": "e16015ca",
    "listMetadata": "4c9e35b1"
  },
  "/blog/tags/intermediate-ec2": {
    "__comp": "6875c492",
    "__context": {
      "plugin": "7e520db1"
    },
    "sidebar": "814f3328",
    "items": [
      {
        "content": "115db2b3"
      },
      {
        "content": "9c814a9e"
      }
    ],
    "tag": "02860158",
    "listMetadata": "878bbf27"
  },
  "/blog/tags/language-tricks-d7e": {
    "__comp": "6875c492",
    "__context": {
      "plugin": "7e520db1"
    },
    "sidebar": "814f3328",
    "items": [
      {
        "content": "115db2b3"
      },
      {
        "content": "9c814a9e"
      }
    ],
    "tag": "95b149d5",
    "listMetadata": "8bbfe270"
  },
  "/blog/tags/solidity-1e8": {
    "__comp": "6875c492",
    "__context": {
      "plugin": "7e520db1"
    },
    "sidebar": "814f3328",
    "items": [
      {
        "content": "115db2b3"
      },
      {
        "content": "9c814a9e"
      }
    ],
    "tag": "5dc20450",
    "listMetadata": "74ae6181"
  },
  "/blog/tags/web-3-e10": {
    "__comp": "6875c492",
    "__context": {
      "plugin": "7e520db1"
    },
    "sidebar": "814f3328",
    "items": [
      {
        "content": "115db2b3"
      },
      {
        "content": "9c814a9e"
      }
    ],
    "tag": "6a3809a9",
    "listMetadata": "37178c25"
  },
  "/blog/welcome-375": {
    "__comp": "ccc49370",
    "__context": {
      "plugin": "7e520db1"
    },
    "sidebar": "814f3328",
    "content": "d9f32620"
  },
  "/markdown-page-0f3": {
    "__comp": "1f391b9e",
    "__context": {
      "plugin": "98c9d051"
    },
    "content": "393be207"
  },
  "/testimonials-bee": {
    "__comp": "1f391b9e",
    "__context": {
      "plugin": "98c9d051"
    },
    "content": "e206c198"
  },
  "/videos-bb6": {
    "__comp": "34f00221",
    "__context": {
      "plugin": "98c9d051"
    },
    "config": "5e9f5e1a"
  },
  "/docs-e83": {
    "__comp": "1be78505",
    "__context": {
      "plugin": "854a673e"
    },
    "versionMetadata": "935f2afb"
  },
  "/docs/category/tutorial---basics-d44": {
    "__comp": "14eb3368",
    "categoryGeneratedIndex": "ea88f2a1"
  },
  "/docs/category/tutorial---extras-f09": {
    "__comp": "14eb3368",
    "categoryGeneratedIndex": "c844b82d"
  },
  "/docs/intro-aed": {
    "__comp": "17896441",
    "content": "0e384e19"
  },
  "/docs/tutorial-basics/congratulations-793": {
    "__comp": "17896441",
    "content": "822bd8ab"
  },
  "/docs/tutorial-basics/create-a-blog-post-68e": {
    "__comp": "17896441",
    "content": "533a09ca"
  },
  "/docs/tutorial-basics/create-a-document-c2d": {
    "__comp": "17896441",
    "content": "1e4232ab"
  },
  "/docs/tutorial-basics/create-a-page-f44": {
    "__comp": "17896441",
    "content": "5c868d36"
  },
  "/docs/tutorial-basics/deploy-your-site-e46": {
    "__comp": "17896441",
    "content": "f55d3e7a"
  },
  "/docs/tutorial-basics/markdown-features-4b7": {
    "__comp": "17896441",
    "content": "18c41134"
  },
  "/docs/tutorial-extras/manage-docs-versions-fdd": {
    "__comp": "17896441",
    "content": "dff1c289"
  },
  "/docs/tutorial-extras/translate-your-site-2d7": {
    "__comp": "17896441",
    "content": "e44a2883"
  },
  "/-b81": {
    "__comp": "c4f5d8e4",
    "__context": {
      "plugin": "98c9d051"
    },
    "config": "5e9f5e1a"
  }
}